pdf_nested_table_extractor/__init__.py
pdf_nested_table_extractor/extractor.py
pdf_nested_table_extractor-0.0.1.dist-info/LICENSE
pdf_nested_table_extractor-0.0.1.dist-info/METADATA
pdf_nested_table_extractor-0.0.1.dist-info/WHEEL
pdf_nested_table_extractor-0.0.1.dist-info/top_level.txt
pdf_nested_table_extractor-0.0.1.dist-info/RECORD
